{
  "scenario": {
    "name": "small",
    "d_ambient": 128,
    "n_curve_features": 16,
    "n_curve_anchors": 32,
    "sparsity_per_token": 3,
    "n_samples": 30000,
    "sae_features": 16,
    "top_k": 4,
    "n_steps": 5000,
    "batch_size": 256,
    "lr": 0.001,
    "n_basis": 8,
    "intrinsic_rank": 4,
    "sparsity_weight": 0.0003,
    "ortho_weight": 0.001,
    "reml_weight": 1.0,
    "continuous_amp": true,
    "noise": 0.02
  },
  "var": 0.9999999403953552,
  "vanilla": {
    "mse": 0.5056725144386292,
    "explained": 0.4943274554209385,
    "alive": 16,
    "params_M": 0.07656,
    "train_seconds": 9.33556056022644,
    "chamfer": {
      "mean": 0.2210393551343173,
      "max": 0.22853690355558826,
      "per_pair": [
        {
          "gt": 0,
          "sae": 13,
          "chamfer": 0.22191613844108835
        },
        {
          "gt": 1,
          "sae": 12,
          "chamfer": 0.22088600349765156
        },
        {
          "gt": 2,
          "sae": 10,
          "chamfer": 0.21502987811516738
        },
        {
          "gt": 3,
          "sae": 0,
          "chamfer": 0.21763814439784873
        },
        {
          "gt": 4,
          "sae": 1,
          "chamfer": 0.22231126104222054
        },
        {
          "gt": 5,
          "sae": 7,
          "chamfer": 0.2179840350736541
        },
        {
          "gt": 6,
          "sae": 9,
          "chamfer": 0.22281758696730225
        },
        {
          "gt": 7,
          "sae": 14,
          "chamfer": 0.22283456709715474
        },
        {
          "gt": 8,
          "sae": 6,
          "chamfer": 0.2233423548767977
        },
        {
          "gt": 9,
          "sae": 8,
          "chamfer": 0.22241942466282077
        },
        {
          "gt": 10,
          "sae": 5,
          "chamfer": 0.22430914322990197
        },
        {
          "gt": 11,
          "sae": 3,
          "chamfer": 0.21649067542078015
        },
        {
          "gt": 12,
          "sae": 15,
          "chamfer": 0.22853690355558826
        },
        {
          "gt": 13,
          "sae": 4,
          "chamfer": 0.21626927241029956
        },
        {
          "gt": 14,
          "sae": 2,
          "chamfer": 0.2219855306401102
        },
        {
          "gt": 15,
          "sae": 11,
          "chamfer": 0.22185876272069063
        }
      ]
    }
  },
  "curve": {
    "mse": 0.23165732622146606,
    "explained": 0.7683426599706804,
    "alive": 16,
    "params_M": 0.09104,
    "train_seconds": 101.08477520942688,
    "chamfer": {
      "mean": 0.14504699435672652,
      "max": 0.1865944463214455,
      "per_pair": [
        {
          "gt": 0,
          "sae": 14,
          "chamfer": 0.1865944463214455
        },
        {
          "gt": 1,
          "sae": 7,
          "chamfer": 0.12234623824129365
        },
        {
          "gt": 2,
          "sae": 5,
          "chamfer": 0.14352846017527698
        },
        {
          "gt": 3,
          "sae": 1,
          "chamfer": 0.1518988595312613
        },
        {
          "gt": 4,
          "sae": 0,
          "chamfer": 0.15221137760972273
        },
        {
          "gt": 5,
          "sae": 6,
          "chamfer": 0.1439143972723614
        },
        {
          "gt": 6,
          "sae": 4,
          "chamfer": 0.12875768186435405
        },
        {
          "gt": 7,
          "sae": 9,
          "chamfer": 0.1351159708997483
        },
        {
          "gt": 8,
          "sae": 13,
          "chamfer": 0.16646059559618243
        },
        {
          "gt": 9,
          "sae": 15,
          "chamfer": 0.14520373170081197
        },
        {
          "gt": 10,
          "sae": 10,
          "chamfer": 0.13928711870632465
        },
        {
          "gt": 11,
          "sae": 12,
          "chamfer": 0.13218527949226508
        },
        {
          "gt": 12,
          "sae": 8,
          "chamfer": 0.1559123864725205
        },
        {
          "gt": 13,
          "sae": 2,
          "chamfer": 0.12377570497932172
        },
        {
          "gt": 14,
          "sae": 11,
          "chamfer": 0.1432254405381555
        },
        {
          "gt": 15,
          "sae": 3,
          "chamfer": 0.1503342203065784
        }
      ]
    }
  }
}